cbbpy/__init__.py
cbbpy/mens_scraper.py
cbbpy/womens_scraper.py
cbbpy/utils/__init__.py
cbbpy/utils/cbbpy_utils.py
cbbpy/utils/mens_team_map.csv
cbbpy/utils/womens_team_map.csv
CBBpy-2.1.2.dist-info/LICENSE
CBBpy-2.1.2.dist-info/METADATA
CBBpy-2.1.2.dist-info/WHEEL
CBBpy-2.1.2.dist-info/top_level.txt
CBBpy-2.1.2.dist-info/RECORD
