Metadata-Version: 2.2
Name: CBBpy
Version: 2.1.2
Summary: A Python-based web scraper for NCAA basketball.
Author: Daniel Cowan
Author-email: dnlcowan37@gmail.com
License: Apache-2.0
Project-URL: homepage, https://github.com/dcstats/CBBpy/
Project-URL: issues, https://github.com/dcstats/CBBpy/issues
Keywords: college,basketball,scraper,scraping,web scraper,data,espn,analysis,science,analytics,cbb,cbbpy,ncaa,ncaam,ncaaw
Classifier: License :: OSI Approved :: Apache Software License
Classifier: Programming Language :: Python :: 3
Classifier: Programming Language :: Python :: 3 :: Only
Classifier: Programming Language :: Python :: 3.9
Classifier: Programming Language :: Python :: 3.10
Classifier: Programming Language :: Python :: 3.11
Classifier: Programming Language :: Python :: 3.12
Classifier: Programming Language :: Python :: 3.13
Requires-Python: >=3.9
License-File: LICENSE
Requires-Dist: pandas>=2.0.0
Requires-Dist: numpy>=2.0.0
Requires-Dist: python-dateutil>=2.4.0
Requires-Dist: pytz>=2022.1
Requires-Dist: tqdm>=4.63.0
Requires-Dist: lxml>=4.9.0
Requires-Dist: joblib>=1.0.0
Requires-Dist: beautifulsoup4>=4.11.0
Requires-Dist: requests>=2.27.0
Requires-Dist: rapidfuzz>=3.9.0
Requires-Dist: platformdirs>=4.0.0
